awsimple/__init__.py
awsimple/__version__.py
awsimple/aws.py
awsimple/cache.py
awsimple/dynamodb.py
awsimple/dynamodb_miv.py
awsimple/exceptions.py
awsimple/logs.py
awsimple/mock.py
awsimple/platform.py
awsimple/pubsub.py
awsimple/py.typed
awsimple/s3.py
awsimple/sns.py
awsimple/sqs.py
awsimple-7.1.0.dist-info/licenses/LICENSE
awsimple-7.1.0.dist-info/licenses/LICENSE.txt
awsimple-7.1.0.dist-info/METADATA
awsimple-7.1.0.dist-info/WHEEL
awsimple-7.1.0.dist-info/top_level.txt
awsimple-7.1.0.dist-info/RECORD
