Metadata-Version: 2.4
Name: awsimple
Version: 7.1.0
Summary: Simple AWS API for S3, DynamoDB, SNS, and SQS
Home-page: https://github.com/jamesabel/awsimple
Download-URL: https://github.com/jamesabel/awsimple
Author: abel
Author-email: j@abel.co
License: MIT License
Project-URL: Documentation, https://awsimple.readthedocs.io/
Keywords: aws,cloud,storage,database,dynamodb,s3
Requires-Python: >3.10
License-File: LICENSE
License-File: LICENSE.txt
Requires-Dist: boto3
Requires-Dist: typeguard
Requires-Dist: hashy>=0.1.1
Requires-Dist: dictim
Requires-Dist: appdirs
Requires-Dist: tobool
Requires-Dist: urllib3
Requires-Dist: python-dateutil
Requires-Dist: yasf
Requires-Dist: strif
Dynamic: author
Dynamic: author-email
Dynamic: description
Dynamic: description-content-type
Dynamic: download-url
Dynamic: home-page
Dynamic: keywords
Dynamic: license
Dynamic: license-file
Dynamic: project-url
Dynamic: requires-dist
Dynamic: requires-python
Dynamic: summary
